sphinxcontrib_lean-0.3.1-py3.8-nspkg.pth
sphinxcontrib/lean.py
sphinxcontrib/leansrc/export_json.lean
tests/__init__.py
tests/test_lean.py
sphinxcontrib_lean-0.3.1.dist-info/COPYING
sphinxcontrib_lean-0.3.1.dist-info/METADATA
sphinxcontrib_lean-0.3.1.dist-info/WHEEL
sphinxcontrib_lean-0.3.1.dist-info/namespace_packages.txt
sphinxcontrib_lean-0.3.1.dist-info/top_level.txt
sphinxcontrib_lean-0.3.1.dist-info/RECORD
