Metadata-Version: 2.1
Name: sphinxcontrib-lean
Version: 0.3.1
Summary: A Sphinx domain for the Lean theorem prover
Home-page: https://github.com/Julian/sphinxcontrib-lean
Author: Julian Berman
Author-email: Julian+sphinxcontrib-lean@GrayVines.com
License: UNKNOWN
Project-URL: Documentation, https://sphinxcontrib-lean.readthedocs.io/en/latest/
Project-URL: Source, https://github.com/Julian/sphinxcontrib-lean
Project-URL: Issues, https://github.com/Julian/sphinxcontrib-lean/issues/
Platform: UNKNOWN
Classifier: Development Status :: 3 - Alpha
Classifier: Operating System :: OS Independent
Classifier: Programming Language :: Python
Classifier: License :: OSI Approved :: MIT License
Classifier: Programming Language :: Python :: 3.7
Classifier: Programming Language :: Python :: 3.8
Classifier: Programming Language :: Python :: 3
Classifier: Programming Language :: Python :: Implementation :: CPython
Classifier: Programming Language :: Python :: Implementation :: PyPy
Requires-Dist: attrs (>=20.2.0)
Requires-Dist: sphinx
